tablestring/TableString.py
tablestring/__init__.py
tablestring/test.py
tablestring/type.py
tablestring/chars/__init__.py
tablestring/chars/border_chars.py
tablestring/helpers/__init__.py
tablestring/helpers/cell_string.py
tablestring/helpers/is_last_element.py
tablestring/helpers/row_cross_border.py
tablestring/helpers/row_outer_border.py
tablestring-0.0.4.dist-info/LICENCE
tablestring-0.0.4.dist-info/METADATA
tablestring-0.0.4.dist-info/WHEEL
tablestring-0.0.4.dist-info/top_level.txt
tablestring-0.0.4.dist-info/RECORD
