Metadata-Version: 2.1
Name: tablestring
Version: 0.0.4
Summary: An ASCII text table renderer.
Author-email: Guy de Winton <guy@codehippie.io>
Project-URL: Homepage, https://gitlab.com/guydewinton/tablestring
Project-URL: Bug Tracker, https://gitlab.com/guydewinton/tablestring/issues
Classifier: Programming Language :: Python :: 3
Classifier: License :: OSI Approved :: MIT License
Classifier: Operating System :: OS Independent
Requires-Python: >=3
License-File: LICENCE
